{
  "diagram_id": "diagram_0153",
  "template": "simple_branch",
  "metadata": {
    "branch": "DXB-BRANCH-01",
    "region": "WEST",
    "site_type": "Hub Site",
    "version": "v0.1",
    "difficulty": "medium"
  },
  "nodes": [
    {
      "id": "WAN-01",
      "type": "cloud_or_wan",
      "bbox": [
        54,
        452,
        134,
        494
      ],
      "zone": "isp"
    },
    {
      "id": "RTR-01",
      "type": "router",
      "bbox": [
        222,
        438,
        274,
        490
      ],
      "zone": "edge"
    },
    {
      "id": "FW-01",
      "type": "firewall",
      "bbox": [
        391,
        433,
        449,
        491
      ],
      "zone": "edge"
    },
    {
      "id": "SW-01",
      "type": "switch",
      "bbox": [
        561,
        436,
        633,
        476
      ],
      "zone": "branch"
    },
    {
      "id": "APP-01",
      "type": "server",
      "bbox": [
        884,
        320,
        950,
        372
      ],
      "zone": "app"
    },
    {
      "id": "APP-02",
      "type": "server",
      "bbox": [
        868,
        575,
        930,
        625
      ],
      "zone": "app"
    },
    {
      "id": "DB-01",
      "type": "database",
      "bbox": [
        1057,
        452,
        1101,
        496
      ],
      "zone": "db"
    }
  ],
  "edges": [
    {
      "source": "WAN-01",
      "target": "RTR-01",
      "label": "API",
      "relationship": "connected_to"
    },
    {
      "source": "RTR-01",
      "target": "FW-01",
      "label": "OSPF",
      "relationship": "connected_to"
    },
    {
      "source": "FW-01",
      "target": "SW-01",
      "label": "VLAN-200",
      "relationship": "connected_to"
    },
    {
      "source": "SW-01",
      "target": "APP-01",
      "label": "HTTPS/443",
      "relationship": "connected_to"
    },
    {
      "source": "SW-01",
      "target": "APP-02",
      "label": "10G",
      "relationship": "connected_to"
    },
    {
      "source": "APP-01",
      "target": "DB-01",
      "label": "VLAN-300",
      "relationship": "connected_to"
    }
  ]
}