{
  "diagram_id": "diagram_0183",
  "template": "dense_enterprise",
  "metadata": {
    "branch": "CHI-BRANCH-02",
    "region": "APAC",
    "site_type": "Large Branch",
    "version": "v0.1",
    "difficulty": "medium"
  },
  "nodes": [
    {
      "id": "WAN-01",
      "type": "cloud_or_wan",
      "bbox": [
        56,
        236,
        136,
        278
      ],
      "zone": "isp"
    },
    {
      "id": "WAN-02",
      "type": "cloud_or_wan",
      "bbox": [
        32,
        554,
        120,
        600
      ],
      "zone": "isp"
    },
    {
      "id": "RTR-01",
      "type": "router",
      "bbox": [
        219,
        210,
        267,
        258
      ],
      "zone": "edge"
    },
    {
      "id": "RTR-02",
      "type": "router",
      "bbox": [
        207,
        563,
        257,
        613
      ],
      "zone": "edge"
    },
    {
      "id": "FW-01",
      "type": "firewall",
      "bbox": [
        331,
        352,
        385,
        406
      ],
      "zone": "edge"
    },
    {
      "id": "FW-02",
      "type": "firewall",
      "bbox": [
        334,
        598,
        390,
        654
      ],
      "zone": "dmz"
    },
    {
      "id": "SW-CORE",
      "type": "switch",
      "bbox": [
        467,
        367,
        535,
        405
      ],
      "zone": "branch"
    },
    {
      "id": "SW-APP",
      "type": "switch",
      "bbox": [
        469,
        597,
        533,
        631
      ],
      "zone": "app"
    },
    {
      "id": "LB-01",
      "type": "load_balancer",
      "bbox": [
        657,
        484,
        717,
        526
      ],
      "zone": "app"
    },
    {
      "id": "MGMT-01",
      "type": "server",
      "bbox": [
        633,
        200,
        693,
        250
      ],
      "zone": "mgmt"
    },
    {
      "id": "APP-01",
      "type": "server",
      "bbox": [
        829,
        356,
        885,
        402
      ],
      "zone": "app"
    },
    {
      "id": "APP-02",
      "type": "server",
      "bbox": [
        839,
        486,
        901,
        536
      ],
      "zone": "app"
    },
    {
      "id": "APP-03",
      "type": "server",
      "bbox": [
        820,
        623,
        884,
        675
      ],
      "zone": "app"
    },
    {
      "id": "APP-04",
      "type": "server",
      "bbox": [
        830,
        749,
        888,
        797
      ],
      "zone": "app"
    },
    {
      "id": "DB-01",
      "type": "database",
      "bbox": [
        1019,
        438,
        1067,
        488
      ],
      "zone": "db"
    },
    {
      "id": "DB-02",
      "type": "database",
      "bbox": [
        1018,
        577,
        1058,
        617
      ],
      "zone": "db"
    },
    {
      "id": "LB-02",
      "type": "load_balancer",
      "bbox": [
        731,
        445,
        793,
        487
      ],
      "zone": "app"
    }
  ],
  "edges": [
    {
      "source": "WAN-01",
      "target": "RTR-01",
      "label": "VLAN-300",
      "relationship": "connected_to"
    },
    {
      "source": "WAN-02",
      "target": "RTR-02",
      "label": "VLAN-200",
      "relationship": "connected_to"
    },
    {
      "source": "RTR-01",
      "target": "FW-01",
      "label": "BGP",
      "relationship": "connected_to"
    },
    {
      "source": "RTR-02",
      "target": "FW-01",
      "label": "API",
      "relationship": "connected_to"
    },
    {
      "source": "FW-01",
      "target": "SW-CORE",
      "label": "VLAN-300",
      "relationship": "connected_to"
    },
    {
      "source": "FW-01",
      "target": "FW-02",
      "label": "HTTPS/443",
      "relationship": "connected_to"
    },
    {
      "source": "FW-02",
      "target": "SW-APP",
      "label": "VPN Tunnel",
      "relationship": "connected_to"
    },
    {
      "source": "SW-CORE",
      "target": "SW-APP",
      "label": "1G",
      "relationship": "connected_to"
    },
    {
      "source": "SW-APP",
      "target": "LB-01",
      "label": "100M",
      "relationship": "connected_to"
    },
    {
      "source": "SW-CORE",
      "target": "MGMT-01",
      "label": "VLAN-300",
      "relationship": "connected_to"
    },
    {
      "source": "LB-01",
      "target": "APP-01",
      "label": "VLAN-100",
      "relationship": "connected_to"
    },
    {
      "source": "LB-01",
      "target": "APP-02",
      "label": "BGP",
      "relationship": "connected_to"
    },
    {
      "source": "LB-01",
      "target": "APP-03",
      "label": "VLAN-300",
      "relationship": "connected_to"
    },
    {
      "source": "LB-01",
      "target": "APP-04",
      "label": "VLAN-200",
      "relationship": "connected_to"
    },
    {
      "source": "APP-01",
      "target": "DB-01",
      "label": "VLAN-200",
      "relationship": "connected_to"
    },
    {
      "source": "APP-02",
      "target": "DB-02",
      "label": "OSPF",
      "relationship": "connected_to"
    },
    {
      "source": "SW-APP",
      "target": "LB-02",
      "label": "VLAN-100",
      "relationship": "connected_to"
    },
    {
      "source": "LB-02",
      "target": "APP-02",
      "label": "Heartbeat",
      "relationship": "connected_to"
    },
    {
      "source": "LB-02",
      "target": "APP-04",
      "label": "SQL/1521",
      "relationship": "connected_to"
    }
  ]
}